odoo/addons/sale_timesheet_limit_date/README.rst
odoo/addons/sale_timesheet_limit_date/__init__.py
odoo/addons/sale_timesheet_limit_date/__manifest__.py
odoo/addons/sale_timesheet_limit_date/i18n/de.po
odoo/addons/sale_timesheet_limit_date/i18n/fr.po
odoo/addons/sale_timesheet_limit_date/i18n/hr_timesheet_limit_sale_date.pot
odoo/addons/sale_timesheet_limit_date/i18n/sale_timesheet_limit_date.pot
odoo/addons/sale_timesheet_limit_date/models/__init__.py
odoo/addons/sale_timesheet_limit_date/models/account_invoice.py
odoo/addons/sale_timesheet_limit_date/models/account_invoice_line.py
odoo/addons/sale_timesheet_limit_date/models/sale_order.py
odoo/addons/sale_timesheet_limit_date/models/sale_order_line.py
odoo/addons/sale_timesheet_limit_date/readme/CONTRIBUTORS.rst
odoo/addons/sale_timesheet_limit_date/readme/DESCRIPTION.rst
odoo/addons/sale_timesheet_limit_date/readme/ROADMAP.rst
odoo/addons/sale_timesheet_limit_date/static/description/icon.png
odoo/addons/sale_timesheet_limit_date/static/description/index.html
odoo/addons/sale_timesheet_limit_date/tests/__init__.py
odoo/addons/sale_timesheet_limit_date/tests/common.py
odoo/addons/sale_timesheet_limit_date/tests/test_invoice_lines.py
odoo/addons/sale_timesheet_limit_date/tests/test_sale_lines.py
odoo/addons/sale_timesheet_limit_date/views/invoice_order_view.xml
odoo/addons/sale_timesheet_limit_date/views/sale_order_view.xml
odoo12_addon_sale_timesheet_limit_date-12.0.1.0.2.dist-info/METADATA
odoo12_addon_sale_timesheet_limit_date-12.0.1.0.2.dist-info/WHEEL
odoo12_addon_sale_timesheet_limit_date-12.0.1.0.2.dist-info/top_level.txt
odoo12_addon_sale_timesheet_limit_date-12.0.1.0.2.dist-info/RECORD
